hed_utils/__init__.py
hed_utils/cli/__init__.py
hed_utils/cli/arguments.py
hed_utils/cli/cli_command.py
hed_utils/cli/csv_search.py
hed_utils/cli/rkill.py
hed_utils/selenium/__init__.py
hed_utils/selenium/constants.py
hed_utils/selenium/factories/__init__.py
hed_utils/selenium/factories/chrome_driver.py
hed_utils/selenium/factories/opera_driver.py
hed_utils/selenium/utils/__init__.py
hed_utils/selenium/utils/element_finder.py
hed_utils/selenium/utils/find_by.py
hed_utils/selenium/utils/js_conditions.py
hed_utils/selenium/utils/shared_driver.py
hed_utils/selenium/utils/window_performance.py
hed_utils/selenium/wrappers/__init__.py
hed_utils/selenium/wrappers/driver_wrapper.py
hed_utils/selenium/wrappers/element_wrapper.py
hed_utils/support/__init__.py
hed_utils/support/checked_param.py
hed_utils/support/config_tool.py
hed_utils/support/google_spreadsheet.py
hed_utils/support/log.py
hed_utils/support/obj.py
hed_utils/support/os_type.py
hed_utils/support/profiler.py
hed_utils/support/ps_tool.py
hed_utils/support/singleton.py
hed_utils/support/table.py
hed_utils/support/text_tool.py
hed_utils/support/time_tool.py
hed_utils/support/web_tool.py
hed_utils/support/file_utils/__init__.py
hed_utils/support/file_utils/csv_file.py
hed_utils/support/file_utils/file_sys.py
hed_utils/support/file_utils/json_file.py
hed_utils/support/file_utils/text_file.py
hed_utils/support/file_utils/xlsx_file.py
hed_utils/support/file_utils/zip_file.py
hed_utils-5.0.0.dist-info/AUTHORS.rst
hed_utils-5.0.0.dist-info/LICENSE.txt
hed_utils-5.0.0.dist-info/METADATA
hed_utils-5.0.0.dist-info/WHEEL
hed_utils-5.0.0.dist-info/entry_points.txt
hed_utils-5.0.0.dist-info/top_level.txt
hed_utils-5.0.0.dist-info/RECORD
