Metadata-Version: 2.1
Name: hed-utils
Version: 5.0.0
Summary: Personal utils collection for (mostly) automation projects.
Home-page: https://github.com/Hrissimir/hed_utils
Author: Hrissimir
Author-email: hrisimir.dakov@gmail.com
License: mit
Project-URL: Documentation, https://pyscaffold.org/
Platform: any
Classifier: Development Status :: 5 - Production/Stable
Classifier: Environment :: Console
Classifier: Intended Audience :: Developers
Classifier: License :: OSI Approved :: MIT License
Classifier: Natural Language :: English
Classifier: Operating System :: MacOS
Classifier: Operating System :: Microsoft
Classifier: Operating System :: POSIX :: Linux
Classifier: Programming Language :: Python
Classifier: Topic :: Software Development :: Libraries :: Python Modules
Classifier: Topic :: Software Development :: Quality Assurance
Classifier: Topic :: Software Development :: Testing
Classifier: Topic :: Utilities
Requires-Python: >=3.6
License-File: LICENSE.txt
License-File: AUTHORS.rst
Requires-Dist: more-itertools (>=8.8.0)
Requires-Dist: tabulate (>=0.8.9)
Requires-Dist: pytz (>=2021.1)
Requires-Dist: tzlocal (>=3.0)
Requires-Dist: python-dateutil (>=2.8.2)
Requires-Dist: recurrent (>=0.4.1)
Requires-Dist: python-dotenv (>=0.19.0)
Requires-Dist: urllib3 (>=1.26.6)
Requires-Dist: requests (>=2.26.0)
Requires-Dist: pathvalidate (>=2.4.1)
Requires-Dist: lxml (>=4.6.3)
Requires-Dist: html5lib (>=1.1)
Requires-Dist: beautifulsoup4 (>=4.9.3)
Requires-Dist: appdirs (>=1.4.4)
Requires-Dist: numpy (>=1.21.2)
Requires-Dist: pandas (>=1.3.2)
Requires-Dist: sqlalchemy (>=1.4.23)
Requires-Dist: selenium (>=3.141.0)
Requires-Dist: webdriverdownloader (>=1.0.0)
Requires-Dist: pillow (>=8.3.1)
Requires-Dist: matplotlib (>=3.4.3)
Requires-Dist: psutil (>=5.8.0)
Requires-Dist: click (>=8.0.1)
Requires-Dist: openpyxl (>=3.0.7)
Requires-Dist: oauth2client (>=4.1.3)
Requires-Dist: gspread (>=4.0.1)
Requires-Dist: faker (>=8.12.1)
Requires-Dist: pycountry (>=20.7.3)
Requires-Dist: importlib-metadata ; python_version < "3.8"
Provides-Extra: testing
Requires-Dist: setuptools ; extra == 'testing'
Requires-Dist: setuptools-scm ; extra == 'testing'
Requires-Dist: wheel ; extra == 'testing'
Requires-Dist: coverage ; extra == 'testing'
Requires-Dist: flake8 ; extra == 'testing'
Requires-Dist: pylint ; extra == 'testing'
Requires-Dist: pytest ; extra == 'testing'
Requires-Dist: pytest-cov ; extra == 'testing'
Requires-Dist: ddt ; extra == 'testing'
Requires-Dist: tox ; extra == 'testing'
Requires-Dist: twine ; extra == 'testing'
